bsm/__init__.py
bsm/argtypes.py
bsm/audit_event.py
bsm/audit_record.py
bsm/bsm.py
bsm/bsm_errors.py
bsm/bsm_h.py
bsm/bsm_token copy.py
bsm/bsm_token.py
bsm/bsm_token_type.py
bsm/version.py
bsm/bin/__init__.py
bsm/bin/praudit.py
bsm/lib/__init__.py
bsm/lib/headers.py
bsm/lib/ioctl.py
bsm/lib/libbsm.py
bsm/lib/libproc.py
openbsm-0.0.2.dist-info/LICENSE
openbsm-0.0.2.dist-info/METADATA
openbsm-0.0.2.dist-info/WHEEL
openbsm-0.0.2.dist-info/entry_points.txt
openbsm-0.0.2.dist-info/top_level.txt
openbsm-0.0.2.dist-info/RECORD
