Metadata-Version: 2.1
Name: openbsm
Version: 0.0.2
Summary: MacOS OpenBSM library
Home-page: https://github.com/haginara/openbsm-python
Author: Jonghak Choi
Author-email: haginara@gmail.com
License: MIT License
Platform: UNKNOWN
Classifier: License :: OSI Approved :: MIT License
Classifier: Programming Language :: Python
Classifier: Programming Language :: Python :: 3.6
Classifier: Programming Language :: Python :: 3.7
Requires-Dist: termcolor (==1.1.0)
